{"precision":[0.001,0.00075,0.0005,0.00025,0.0001],"method":"MC","sample_size":50,"minimum_level":3,"maximum_level":25,"level_growth_factor":1.5,"wind_speed_growth_factor":2,"uncertainties":[{"parameter":"windspeed","pdf_type":"normal","multi_dimensional":false,"p90_percentage":8},{"parameter":"wakeeffect","pdf_type":"normal","multi_dimensional":false,"p90_percentage":3},{"parameter":"ctcurve","pdf_type":"normal","multi_dimensional":false,"p90_percentage":2},{"parameter":"surfaceroughness","pdf_type":"normal","multi_dimensional":false,"p90_percentage":0.021},{"parameter":"powercurve","pdf_type":"normal","multi_dimensional":false,"p90_percentage":2},{"parameter":"plantperformance","pdf_type":"normal","multi_dimensional":false,"p90_percentage":2.3},{"parameter":"capitalcosts","pdf_type":"normal","multi_dimensional":false,"p90_percentage":3},{"parameter":"omcosts","pdf_type":"normal","multi_dimensional":false,"p90_percentage":3},{"parameter":"discountrate","pdf_type":"normal","multi_dimensional":false,"p90_percentage":4},{"parameter":"energyprice","pdf_type":"normal","multi_dimensional":false,"p90_percentage":0.1}],"sparse_grid":{"node_type":"CC","level":3}}